Metadata-Version: 2.1
Name: Takaya
Version: 0.0.1
Summary: YOU CAN REVERSE,REMOVE AND COUNT VOWELS IN THE STRING
Author: SASHIN
Author-email: sashin_ranjitkar@takaya.co.jp
License: MIT
Keywords: REVERSE,REMOVE,VOWEL_COUNT
Platform: UNKNOWN
License-File: LICENSE.txt
